botframework/__init__.py
botframework/botframework.py
botframework/botframework_utils.py
botframework/cex_proxy.py
botframework/indicator_aggregator_botframework.py
botframework/kafka_producer.py
botframework/market_mgr.py
botframework/portfolio_mgr.py
botframework/scheduler.py
botframework/signal_mgr.py
botframework/strategy.py
botframework/trade_mgr.py
botframework/trading_timeframe.py
botframework/models/__init__.py
botframework/models/position_capacity.py
tks_bot_framework-1.0.35.dist-info/licenses/LICENSE
tks_bot_framework-1.0.35.dist-info/METADATA
tks_bot_framework-1.0.35.dist-info/WHEEL
tks_bot_framework-1.0.35.dist-info/top_level.txt
tks_bot_framework-1.0.35.dist-info/RECORD
