Metadata-Version: 2.4
Name: tks-bot-framework
Version: 1.0.35
Summary: A bot framework for signal providers for Freya Alpha.
Author-email: "Karin Richner, Brayan Svan" <hello@thekarasystem.com>
Project-URL: Homepage, https://github.com/The-Kara-System/tks-bot-framework
Keywords: finance,trading,models
Classifier: License :: OSI Approved :: MIT License
Classifier: Programming Language :: Python
Requires-Python: >=3.9
License-File: LICENSE
Requires-Dist: sqlmodel
Requires-Dist: tomli; python_version < "3.11"
Provides-Extra: dev
Requires-Dist: black; extra == "dev"
Requires-Dist: bumpver; extra == "dev"
Requires-Dist: isort; extra == "dev"
Requires-Dist: pip-tools; extra == "dev"
Requires-Dist: pytest; extra == "dev"
Dynamic: license-file
